<?xml version="1.0" encoding="UTF-8"?>
<quiz>
  <question type="category">
    <category>
      <text>__Category Name__</text>
    </category>
  </question>
<!-- Question entry 1.0-->
  <question type="multichoice">
    <name>
      <text>
<![CDATA[Was dachte sich Valerie nachdem sie ihn geküsst hat?]]>
      </text>
    </name>
    <questiontext format="html">
      <text>
<![CDATA[Was dachte sich Valerie nachdem sie ihn geküsst hat?]]>
      </text>
    </questiontext>
    <answer fraction="100.000">
      <text>
<![CDATA[dass Herr Liebig das gleiche für sie empfindet]]>
      </text>
    </answer>
    <answer fraction="0">
      <text>
<![CDATA[dass sie sich jetzt einen anderen suchen muss]]>
      </text>
    </answer>
    <answer fraction="0">
      <text>
<![CDATA[dass sie jetzt den Test nochmal wiederholen muss]]>
      </text>
    </answer>
    <shuffleanswers>1</shuffleanswers>
    <single>true</single>
    <answernumbering>123</answernumbering>
  </question>
<!-- Question entry 2.0-->
  <question type="multichoice">
    <name>
      <text>
<![CDATA[Warum schreit die Direktorin?]]>
      </text>
    </name>
    <questiontext format="html">
      <text>
<![CDATA[Warum schreit die Direktorin?]]>
      </text>
    </questiontext>
    <answer fraction="100.000">
      <text>
<![CDATA[weil sie glaubt, dass Valerie Herrn Liebig umgebracht (=killed) hat]]>
      </text>
    </answer>
    <answer fraction="0">
      <text>
<![CDATA[weil sie wütend auf Valerie ist]]>
      </text>
    </answer>
    <answer fraction="0">
      <text>
<![CDATA[weil sie an was anderes gedacht hat]]>
      </text>
    </answer>
    <shuffleanswers>1</shuffleanswers>
    <single>true</single>
    <answernumbering>123</answernumbering>
  </question>
<!-- Question entry 3.0-->
  <question type="multichoice">
    <name>
      <text>
<![CDATA[Hat Valerie Herrn Liebig umgebracht?]]>
      </text>
    </name>
    <questiontext format="html">
      <text>
<![CDATA[Hat Valerie Herrn Liebig umgebracht?]]>
      </text>
    </questiontext>
    <answer fraction="100.000">
      <text>
<![CDATA[nein]]>
      </text>
    </answer>
    <answer fraction="0">
      <text>
<![CDATA[ja]]>
      </text>
    </answer>
    <answer fraction="0">
      <text>
<![CDATA[Wir wissen es nicht.]]>
      </text>
    </answer>
    <shuffleanswers>1</shuffleanswers>
    <single>true</single>
    <answernumbering>123</answernumbering>
  </question>
<!-- Question entry 4.0-->
  <question type="multichoice">
    <name>
      <text>
<![CDATA[Warum schämt sich Valerie?]]>
      </text>
    </name>
    <questiontext format="html">
      <text>
<![CDATA[Warum schämt sich Valerie?]]>
      </text>
    </questiontext>
    <answer fraction="100.000">
      <text>
<![CDATA[weil sie Herrn Liebig als Heiratsschwindler (marriage swindler) bezeichnet hat]]>
      </text>
    </answer>
    <answer fraction="0">
      <text>
<![CDATA[weil sie Herrn Liebig geküsst hat]]>
      </text>
    </answer>
    <answer fraction="0">
      <text>
<![CDATA[weil Frau Richter sie anstarrt (=to stare)]]>
      </text>
    </answer>
    <shuffleanswers>1</shuffleanswers>
    <single>true</single>
    <answernumbering>123</answernumbering>
  </question>
</quiz>