<?xml version="1.0" encoding="UTF-8"?>
<quiz>
  <question type="category">
    <category>
      <text>__Category Name__</text>
    </category>
  </question>
<!-- Question entry 1.0-->
  <question type="multichoice">
    <name>
      <text>
<![CDATA[Welche Dinger werden immer kleiner?]]>
      </text>
    </name>
    <questiontext format="html">
      <text>
<![CDATA[Welche Dinger werden immer kleiner?]]>
      </text>
    </questiontext>
    <answer fraction="100.000">
      <text>
<![CDATA[Kopfhörer]]>
      </text>
    </answer>
    <answer fraction="0">
      <text>
<![CDATA[Handys]]>
      </text>
    </answer>
    <answer fraction="0">
      <text>
<![CDATA[Kinder]]>
      </text>
    </answer>
    <shuffleanswers>1</shuffleanswers>
    <single>true</single>
    <answernumbering>123</answernumbering>
  </question>
<!-- Question entry 2.0-->
  <question type="multichoice">
    <name>
      <text>
<![CDATA[Wer erschreckt Markus?]]>
      </text>
    </name>
    <questiontext format="html">
      <text>
<![CDATA[Wer erschreckt Markus?]]>
      </text>
    </questiontext>
    <answer fraction="100.000">
      <text>
<![CDATA[Simone]]>
      </text>
    </answer>
    <answer fraction="0">
      <text>
<![CDATA[Stefan]]>
      </text>
    </answer>
    <answer fraction="0">
      <text>
<![CDATA[er sich selbst]]>
      </text>
    </answer>
    <shuffleanswers>1</shuffleanswers>
    <single>true</single>
    <answernumbering>123</answernumbering>
  </question>
<!-- Question entry 3.0-->
  <question type="multichoice">
    <name>
      <text>
<![CDATA[Wovon ist Simone genervt?]]>
      </text>
    </name>
    <questiontext format="html">
      <text>
<![CDATA[Wovon ist Simone genervt?]]>
      </text>
    </questiontext>
    <answer fraction="100.000">
      <text>
<![CDATA[vom Augenrollen]]>
      </text>
    </answer>
    <answer fraction="0">
      <text>
<![CDATA[von Ihrer Unterhaltung mit Markus]]>
      </text>
    </answer>
    <answer fraction="0">
      <text>
<![CDATA[von Markus Handy]]>
      </text>
    </answer>
    <shuffleanswers>1</shuffleanswers>
    <single>true</single>
    <answernumbering>123</answernumbering>
  </question>
<!-- Question entry 4.0-->
  <question type="multichoice">
    <name>
      <text>
<![CDATA[Wie heißt Markus mit Nachnamen?]]>
      </text>
    </name>
    <questiontext format="html">
      <text>
<![CDATA[Wie heißt Markus mit Nachnamen?]]>
      </text>
    </questiontext>
    <answer fraction="100.000">
      <text>
<![CDATA[Huber]]>
      </text>
    </answer>
    <answer fraction="0">
      <text>
<![CDATA[Richter]]>
      </text>
    </answer>
    <answer fraction="0">
      <text>
<![CDATA[Lichtenau]]>
      </text>
    </answer>
    <shuffleanswers>1</shuffleanswers>
    <single>true</single>
    <answernumbering>123</answernumbering>
  </question>
</quiz>