<?xml version="1.0" encoding="UTF-8"?>
<quiz>
  <question type="category">
    <category>
      <text>__Category Name__</text>
    </category>
  </question>
<!-- Question entry 1.0-->
  <question type="multichoice">
    <name>
      <text>
<![CDATA[Wo befinden sich Valerie und Simone und Stefan?]]>
      </text>
    </name>
    <questiontext format="html">
      <text>
<![CDATA[Wo befinden sich Valerie und Simone und Stefan?]]>
      </text>
    </questiontext>
    <answer fraction="100.000">
      <text>
<![CDATA[im Lehrerzimmer]]>
      </text>
    </answer>
    <answer fraction="0">
      <text>
<![CDATA[vor der Toilette]]>
      </text>
    </answer>
    <answer fraction="0">
      <text>
<![CDATA[auf dem Pausenhof]]>
      </text>
    </answer>
    <shuffleanswers>1</shuffleanswers>
    <single>true</single>
    <answernumbering>123</answernumbering>
  </question>
<!-- Question entry 2.0-->
  <question type="multichoice">
    <name>
      <text>
<![CDATA[Wie sieht Frau Richter aus?]]>
      </text>
    </name>
    <questiontext format="html">
      <text>
<![CDATA[Wie sieht Frau Richter aus?]]>
      </text>
    </questiontext>
    <answer fraction="100.000">
      <text>
<![CDATA[Sie trägt eine Brille.]]>
      </text>
    </answer>
    <answer fraction="0">
      <text>
<![CDATA[Sie hat ein Piercing.]]>
      </text>
    </answer>
    <answer fraction="0">
      <text>
<![CDATA[Sie trägt viel Makeup.]]>
      </text>
    </answer>
    <shuffleanswers>1</shuffleanswers>
    <single>true</single>
    <answernumbering>123</answernumbering>
  </question>
<!-- Question entry 3.0-->
  <question type="multichoice">
    <name>
      <text>
<![CDATA[Wann hört Valerie auf zu weinen?]]>
      </text>
    </name>
    <questiontext format="html">
      <text>
<![CDATA[Wann hört Valerie auf zu weinen?]]>
      </text>
    </questiontext>
    <answer fraction="100.000">
      <text>
<![CDATA[als sie Frau Richters Stimme hört]]>
      </text>
    </answer>
    <answer fraction="0">
      <text>
<![CDATA[als sie ein Taschentuch von Simone bekommt]]>
      </text>
    </answer>
    <answer fraction="0">
      <text>
<![CDATA[als es ihr wieder besser geht]]>
      </text>
    </answer>
    <shuffleanswers>1</shuffleanswers>
    <single>true</single>
    <answernumbering>123</answernumbering>
  </question>
<!-- Question entry 4.0-->
  <question type="multichoice">
    <name>
      <text>
<![CDATA[Wem sieht Herr Liebig ähnlich?]]>
      </text>
    </name>
    <questiontext format="html">
      <text>
<![CDATA[Wem sieht Herr Liebig ähnlich?]]>
      </text>
    </questiontext>
    <answer fraction="100.000">
      <text>
<![CDATA[Brad Pitt]]>
      </text>
    </answer>
    <answer fraction="0">
      <text>
<![CDATA[Chris Pratt]]>
      </text>
    </answer>
    <answer fraction="0">
      <text>
<![CDATA[Bad Pritt]]>
      </text>
    </answer>
    <shuffleanswers>1</shuffleanswers>
    <single>true</single>
    <answernumbering>123</answernumbering>
  </question>
</quiz>